{
  "popular-country": [
    {
      "name": "Russia",
      "img-url": "xyz.png",
      "url": "/country/russia"
    },
    {
      "name": "Armenia",
      "img-url": "xyz.png",
      "url": "/country/armenia"
    },
    {
      "name": "Georgia",
      "img-url": "xyz.png",
      "url": "/country/georgia"
    },
    {
      "name": "Kazakhstan",
      "img-url": "xyz.png",
      "url": "/country/kazakhstan"
    },
    {
      "name": "Kyrgyzstan",
      "img-url": "xyz.png",
      "url": "/country/kyrgyzstan"
    },
    {
      "name": "Uzbekistan",
      "img-url": "xyz.png",
      "url": "/country/uzbekistan"
    }
  ]
}
